notion_cli_py/__init__.py
notion_cli_py/cli.py
notion_cli_py/client/client.py
notion_cli_py/configure/configure.py
notion_cli_py/operations/append.py
notion_cli_py/operations/create.py
notion_cli_py/operations/delete.py
notion_cli_py/operations/get.py
notion_cli_py/operations/query.py
notion_cli_py/operations/search.py
notion_cli_py/operations/update.py
notion_cli_py/utils/confirm.py
notion_cli_py/utils/input_handler.py
notion_cli_py/utils/logger.py
notion_cli_py/utils/read_file.py
notion_cli_py-1.0.1.dist-info/entry_points.txt
notion_cli_py-1.0.1.dist-info/WHEEL
notion_cli_py-1.0.1.dist-info/METADATA
notion_cli_py-1.0.1.dist-info/RECORD
