Metadata-Version: 2.1
Name: notion-cli-py
Version: 1.0.1
Summary: NotionCLI - The CLI tool for Notion.co (https://www.notion.so/ja-jp/product).
Home-page: https://github.com/fieldflat
License: MIT
Author: Tomonori HIRATA
Author-email: tomonori4565@icloud.com
Requires-Python: >=3.9,<4.0
Classifier: License :: OSI Approved :: MIT License
Classifier: Programming Language :: Python :: 3
Classifier: Programming Language :: Python :: 3.10
Classifier: Programming Language :: Python :: 3.9
Requires-Dist: fire (>=0.4.0,<0.5.0)
Requires-Dist: requests (>=2.27.1,<3.0.0)
Requires-Dist: tabulate (>=0.8.9,<0.9.0)
Requires-Dist: toml (>=0.10.2,<0.11.0)
Project-URL: Repository, https://github.com/fieldflat/notion-cli-py
